pymwalib/__init__.py
pymwalib/antenna.py
pymwalib/baseline.py
pymwalib/coarse_channel.py
pymwalib/common.py
pymwalib/constants.py
pymwalib/correlator_context.py
pymwalib/errors.py
pymwalib/metafits_context.py
pymwalib/metafits_metadata.py
pymwalib/mwalib.py
pymwalib/rfinput.py
pymwalib/timestep.py
pymwalib/version.py
pymwalib/voltage_context.py
pymwalib-0.16.3.dist-info/LICENSE.txt
pymwalib-0.16.3.dist-info/METADATA
pymwalib-0.16.3.dist-info/WHEEL
pymwalib-0.16.3.dist-info/top_level.txt
pymwalib-0.16.3.dist-info/RECORD
