Metadata-Version: 2.1
Name: pymwalib
Version: 0.16.3
Summary: A python wrapper for mwalib to work with raw data from the Murchison Widefield Array (MWA)
Home-page: https://github.com/MWATelescope/pymwalib
Author: Greg Sleap
Author-email: greg.sleap@curtin.edu.au
License: 'mpl-2.0'
Project-URL: Bug Tracker, https://github.com/MWATelescope/pymwalib/issues
Keywords: MWA,radioastronomy
Classifier: Development Status :: 4 - Beta
Classifier: Intended Audience :: Science/Research
Classifier: Topic :: Scientific/Engineering :: Astronomy
Classifier: License :: OSI Approved :: Mozilla Public License 2.0 (MPL 2.0)
Classifier: Programming Language :: Python :: 3.8
Classifier: Programming Language :: Python :: 3.9
Classifier: Programming Language :: Python :: 3.10
Requires-Python: >=3.6
License-File: LICENSE.txt
